tap_zoho_inventory/__init__.py
tap_zoho_inventory/auth.py
tap_zoho_inventory/client.py
tap_zoho_inventory/config.json
tap_zoho_inventory/streams.py
tap_zoho_inventory/tap.py
tap_zoho_inventory/tests/__init__.py
tap_zoho_inventory/tests/test_core.py
tap_zoho_inventory-0.0.1.dist-info/METADATA
tap_zoho_inventory-0.0.1.dist-info/WHEEL
tap_zoho_inventory-0.0.1.dist-info/entry_points.txt
tap_zoho_inventory-0.0.1.dist-info/RECORD
